django_refresh_migration/__init__.py
django_refresh_migration/app.py
django_refresh_migration/management/__init__.py
django_refresh_migration/management/commands/__init__.py
django_refresh_migration/management/commands/refresh_migration.py
django_refresh_migration-0.0.1.dist-info/LICENSE
django_refresh_migration-0.0.1.dist-info/METADATA
django_refresh_migration-0.0.1.dist-info/WHEEL
django_refresh_migration-0.0.1.dist-info/RECORD
