Metadata-Version: 2.3
Name: django-refresh-migration
Version: 0.0.1
Summary: 
License: MIT
Author: Tum Nuttapat
Author-email: nuttapat.forwork@gmail.com
Requires-Python: >=3.10
Classifier: License :: OSI Approved :: MIT License
Classifier: Programming Language :: Python :: 3
Classifier: Programming Language :: Python :: 3.10
Classifier: Programming Language :: Python :: 3.11
Classifier: Programming Language :: Python :: 3.12
Classifier: Programming Language :: Python :: 3.13
Requires-Dist: django (>=4.2.0,<6.0.0)
